prompt_vault/__init__.py
prompt_vault/auth.py
prompt_vault/cli.py
prompt_vault/config.py
prompt_vault/install.py
prompt_vault/shim.py
prompt_vault/sync.py
cc_vault-0.1.2.dist-info/METADATA
cc_vault-0.1.2.dist-info/WHEEL
cc_vault-0.1.2.dist-info/entry_points.txt
cc_vault-0.1.2.dist-info/licenses/LICENSE
cc_vault-0.1.2.dist-info/RECORD
