Metadata-Version: 2.4
Name: cc-vault
Version: 0.1.2
Summary: Automatic Claude Code session sync
Project-URL: Homepage, https://github.com/rstar327/prompt-vault
Project-URL: Repository, https://github.com/rstar327/prompt-vault
Author: rstar327
License-Expression: MIT
License-File: LICENSE
Keywords: ai,claude,logging,sync
Classifier: Development Status :: 3 - Alpha
Classifier: Environment :: Console
Classifier: Intended Audience :: Developers
Classifier: License :: OSI Approved :: MIT License
Classifier: Programming Language :: Python :: 3
Classifier: Programming Language :: Python :: 3.10
Classifier: Programming Language :: Python :: 3.11
Classifier: Programming Language :: Python :: 3.12
Requires-Python: >=3.10
Requires-Dist: pyyaml>=6.0
Requires-Dist: requests>=2.28.0
Provides-Extra: dev
Requires-Dist: black; extra == 'dev'
Requires-Dist: pytest>=7.0; extra == 'dev'
Requires-Dist: ruff; extra == 'dev'
